README.md
pyproject.toml
src/streamlit_localstorage_bulk/__init__.py
src/streamlit_localstorage_bulk/cache.py
src/streamlit_localstorage_bulk/constants.py
src/streamlit_localstorage_bulk/core.py
src/streamlit_localstorage_bulk/logger.py
src/streamlit_localstorage_bulk/util.py
src/streamlit_localstorage_bulk.egg-info/PKG-INFO
src/streamlit_localstorage_bulk.egg-info/SOURCES.txt
src/streamlit_localstorage_bulk.egg-info/dependency_links.txt
src/streamlit_localstorage_bulk.egg-info/requires.txt
src/streamlit_localstorage_bulk.egg-info/top_level.txt
tests/test_util.py