Metadata-Version: 2.1
Name: streamlit-localstorage-bulk
Version: 0.1.0
Summary: Handles localstorage with Streamlit.
Author-email: Hiroshi Toyama <toyama0919@gmail.com>
Project-URL: Homepage, https://github.com/toyama0919/streamlit-localstorage-bulk
Keywords: streamlit,tool,localstorage
Classifier: Programming Language :: Python :: 3.8
Classifier: Programming Language :: Python :: 3.9
Classifier: Programming Language :: Python :: 3.10
Classifier: Programming Language :: Python :: 3.11
Requires-Python: >=3.8
Requires-Dist: streamlit
Requires-Dist: streamlit-js
Provides-Extra: test
Requires-Dist: tox; extra == "test"
Requires-Dist: pytest; extra == "test"
Requires-Dist: mock; extra == "test"
